anyio_sqlite/__init__.py
anyio_sqlite/_exceptions.py
anyio_sqlite/_types.py
anyio_sqlite/_worker.py
anyio_sqlite/blob.py
anyio_sqlite/connection.py
anyio_sqlite/cursor.py
anyio_sqlite/py.typed
anyio_sqlite-0.3.0.dist-info/licenses/LICENSE-APACHE
anyio_sqlite-0.3.0.dist-info/licenses/LICENSE-MIT
anyio_sqlite-0.3.0.dist-info/WHEEL
anyio_sqlite-0.3.0.dist-info/METADATA
anyio_sqlite-0.3.0.dist-info/RECORD
