Metadata-Version: 2.4
Name: anyio-sqlite
Version: 0.3.0
Summary: anyio bridge to the standard sqlite3 module
Author: beerpsi
Author-email: beerpsi <beerpsi@duck.com>
License-Expression: Apache-2.0 OR MIT
License-File: LICENSE-APACHE
License-File: LICENSE-MIT
Classifier: Development Status :: 4 - Beta
Classifier: Framework :: AnyIO
Classifier: Intended Audience :: Developers
Classifier: License :: OSI Approved :: Apache Software License
Classifier: License :: OSI Approved :: MIT License
Classifier: Programming Language :: Python :: 3.9
Classifier: Programming Language :: Python :: 3.10
Classifier: Programming Language :: Python :: 3.11
Classifier: Programming Language :: Python :: 3.12
Classifier: Programming Language :: Python :: 3.13
Classifier: Programming Language :: Python :: 3.14
Classifier: Topic :: Software Development :: Libraries
Requires-Dist: aioresult~=1.1
Requires-Dist: anyio~=4.11
Requires-Dist: typing-extensions~=4.0
Requires-Python: >=3.9
Project-URL: funding, https://ko-fi.com/beerpsi_
Project-URL: github, https://github.com/beer-psi/anyio-sqlite
Project-URL: issues, https://github.com/beer-psi/anyio-sqlite/issues
